CONTRIBUTING.md
LICENSE.md
LICENSE.txt
MANIFEST.in
README.md
README.rst
install_requires.txt
manage.py
pytest.ini
requirements.benchmark.txt
requirements.txt
setup.cfg
setup.py
tox.ini
benchmarks/__init__.py
benchmarks/drest.py
benchmarks/drf.py
benchmarks/models.py
benchmarks/settings.py
benchmarks/test_bench.py
benchmarks/urls.py
django_dynamic_rest.egg-info/PKG-INFO
django_dynamic_rest.egg-info/SOURCES.txt
django_dynamic_rest.egg-info/dependency_links.txt
django_dynamic_rest.egg-info/requires.txt
django_dynamic_rest.egg-info/top_level.txt
dynamic_rest/__init__.py
dynamic_rest/bases.py
dynamic_rest/conf.py
dynamic_rest/constants.py
dynamic_rest/datastructures.py
dynamic_rest/filters.py
dynamic_rest/links.py
dynamic_rest/meta.py
dynamic_rest/metadata.py
dynamic_rest/pagination.py
dynamic_rest/patches.py
dynamic_rest/prefetch.py
dynamic_rest/processors.py
dynamic_rest/related.py
dynamic_rest/renderers.py
dynamic_rest/routers.py
dynamic_rest/serializers.py
dynamic_rest/tagged.py
dynamic_rest/utils.py
dynamic_rest/viewsets.py
dynamic_rest/blueprints/api/__init__.py
dynamic_rest/blueprints/api/context.py
dynamic_rest/blueprints/api/templates/{{app}}/__init__.py.j2
dynamic_rest/blueprints/api/templates/{{app}}/api/__init__.py.j2
dynamic_rest/blueprints/api/templates/{{app}}/api/urls.py.j2
dynamic_rest/blueprints/api/templates/{{app}}/api/{{version}}/__init__.py.j2
dynamic_rest/blueprints/api/templates/{{app}}/api/{{version}}/urls.py.j2
dynamic_rest/blueprints/api/templates/{{app}}/api/{{version}}/serializers/__init__.py.j2
dynamic_rest/blueprints/api/templates/{{app}}/api/{{version}}/serializers/base.py.j2
dynamic_rest/blueprints/api/templates/{{app}}/api/{{version}}/serializers/{{name}}.py.j2
dynamic_rest/blueprints/api/templates/{{app}}/api/{{version}}/views/__init__.py.j2
dynamic_rest/blueprints/api/templates/{{app}}/api/{{version}}/views/base.py.j2
dynamic_rest/blueprints/api/templates/{{app}}/api/{{version}}/views/{{name}}.py.j2
dynamic_rest/blueprints/init/__init__.py
dynamic_rest/blueprints/init/context.py
dynamic_rest/blueprints/init/templates/{{app}}/settings.py.j2
dynamic_rest/fields/__init__.py
dynamic_rest/fields/common.py
dynamic_rest/fields/fields.py
