Metadata-Version: 2.1
Name: django-dynamic-rest
Version: 2.1.0
Summary: Dynamic API support to Django REST Framework.
Home-page: https://github.com/hunchat/django-dynamic-rest
License: UNKNOWN
Platform: UNKNOWN
Classifier: Framework :: Django
Classifier: Intended Audience :: Developers
Classifier: License :: OSI Approved :: BSD License
Classifier: Programming Language :: Python
Classifier: Programming Language :: Python :: 3
Classifier: Programming Language :: Python :: 3.6
Classifier: Programming Language :: Python :: 3.7
Classifier: Programming Language :: Python :: 3.8
Classifier: Topic :: Software Development :: Libraries :: Python Modules
License-File: LICENSE.md
License-File: LICENSE.txt
